Metadata-Version: 2.1
Name: flaskdesign
Version: 0.0.1
Summary: Design patterns for projects using flask based in blueprints
Home-page: https://github.com/MichaelDeMattos/flask-design
Author: Michael M. Ortiz
Author-email: chelmto3000@gmail.com
License: MIT License
Keywords: flaskdesign
Platform: UNKNOWN
License-File: LICENCE
